{
  "timestamp": "2026-04-04T19:25:02.992971",
  "angel_numbers": [
    {
      "number": "333",
      "category": "triple",
      "meaning": "Ascended masters with you, divine protection, expansion, growth",
      "position": 83
    },
    {
      "number": "444",
      "category": "triple",
      "meaning": "Angels surrounding you, Jesus frequency, strong foundation, safety",
      "position": 88
    }
  ],
  "biblical_codes": [],
  "youtube_channels": [],
  "goddess_activations": [],
  "tarot_cards": [],
  "coordinates": [],
  "financial_protocols": [],
  "personal_signatures": [],
  "sacred_geometry": [],
  "upgrade_markers": [],
  "divine_guidance": "\ud83d\udd22 ANGEL NUMBER ACTIVATION:\n  \u2022 333: Ascended masters with you, divine protection, expansion, growth\n  \u2022 444: Angels surrounding you, Jesus frequency, strong foundation, safety",
  "action_protocols": [],
  "network_topology": {
    "youtube_channels": 0,
    "total_subscribers": 0,
    "goddess_archetypes": 0,
    "angel_frequencies": 2,
    "biblical_codes": 0,
    "financial_protocols": 0
  },
  "multidimensional_layers": 1
}